<?xml version="1.0" encoding="UTF-8"?>
<category name="TSTYPE"><!-- 계좌이동제 이체종류코드 변환 -->
  <code key="1" order="0"><![CDATA[지로 자동이체]]></code>
  <code key="2" order="0"><![CDATA[은행공동CMS]]></code>
  <code key="3" order="0"><![CDATA[펌뱅킹]]></code>
  <code key="4" order="0"><![CDATA[은행카드]]></code>
  <code key="5" order="0"><![CDATA[관리비]]></code>
  <code key="8" order="0"><![CDATA[FIRM > GIRO]]></code>
  <code key="9" order="0"><![CDATA[FIRM > CMS]]></code>
  <code key="E" order="0"><![CDATA[ 알수없는값]]></code>
</category>

