<?xml version="1.0" encoding="UTF-8"?>
<응답부>
  <ScfbHeader>
    <TotalLength>00750</TotalLength>
    <ChannelType>I</ChannelType>
    <WASTranNo>000072</WASTranNo>
    <EGMSTranNo>000164</EGMSTranNo>
    <UserIP>000.000.000.000</UserIP>
    <AppVersion>1.6.7</AppVersion>
    <VFDSDeviceKey></VFDSDeviceKey>
    <WASTYPE></WASTYPE>
    <_DE2E123_EncSK></_DE2E123_EncSK>
    <_DVKEY_EncSK></_DVKEY_EncSK>
    <IMSTRANCD>TI1IBK01</IMSTRANCD>
    <BLK></BLK>
    <INCHANNEL>G</INCHANNEL>
    <BRANCH>0998</BRANCH>
    <LOTNO>000</LOTNO>
    <TCNO>1</TCNO>
    <INTERTYPE>3</INTERTYPE>
    <INTERNO>1</INTERNO>
    <COUNTERINFO1></COUNTERINFO1>
    <COUNTERINFO2></COUNTERINFO2>
    <BRANCHNO>860</BRANCHNO>
    <CONVTERSCR></CONVTERSCR>
    <RES>0</RES>
    <MSGINFOBLK></MSGINFOBLK>
    <MODEINFO></MODEINFO>
    <DESTP></DESTP>
    <JOBTP>GP</JOBTP>
    <INCLASSCD>D006</INCLASSCD>
    <CTRLCDNO></CTRLCDNO>
    <RESCDNO></RESCDNO>
    <STFLAG1></STFLAG1>
    <STFLAG2></STFLAG2>
    <STFLAG3></STFLAG3>
    <STFLAG4></STFLAG4>
    <INLINE></INLINE>
    <PFKEY></PFKEY>
    <RES1>00696</RES1>
    <BRANCHSAV></BRANCHSAV>
    <DEALSAV>998</DEALSAV>
    <INTERSAV>AINTIB</INTERSAV>
    <NEWFORMATTP>NEW</NEWFORMATTP>
    <OUTERRCD></OUTERRCD>
    <OUTLU></OUTLU>
    <SOURCEOUTLU>DP</SOURCEOUTLU>
    <INIJOBCLA>GP</INIJOBCLA>
    <INIINCLA>D006</INIINCLA>
    <FBTPROCESSTRNSNO></FBTPROCESSTRNSNO>
    <RES2>35544</RES2>
    <TRSTP>0210</TRSTP>
    <TRSNO>000164</TRSNO>
    <SVCCD>006</SVCCD>
    <PROCESSTP>L</PROCESSTP>
    <LOCALTP>P1</LOCALTP>
    <VANTP>47</VANTP>
    <VAPCNLNO>000</VAPCNLNO>
    <FSPID>00000000</FSPID>
    <INOUTCNLTP>W</INOUTCNLTP>
    <SENDDATE>20251215</SENDDATE>
    <SENDTIME>095224</SENDTIME>
    <SENDSYSTEM>P</SENDSYSTEM>
    <ERRORCODE>0000</ERRORCODE>
    <RESPONSECODE>0</RESPONSECODE>
    <DISPLAYTYPE></DISPLAYTYPE>
    <ERRORLOCATION>00</ERRORLOCATION>
    <FILLER></FILLER>
  </ScfbHeader>
  <RES_DATA_PART>
    <UserID>LOANTE80</UserID>
    <TSPassword>99999999</TSPassword>
    <DeptPersonName>업무테스트　　　　　　　　　　</DeptPersonName>
    <ZipCode>110858</ZipCode>
    <Address>５８　두산위브파빌리온　１２１８호　　　　　　　　　　　　　</Address>
    <TelCode>010 11111111</TelCode>
    <EmailAddr>TEST@SC.COM</EmailAddr>
    <PersonOrCompanyCode>1</PersonOrCompanyCode>
    <RegNo>8007071999994</RegNo>
    <InforGubun></InforGubun>
    <SafeCardKind>1</SafeCardKind>
    <SecurityIndex>000000</SecurityIndex>
    <TransGubun>1</TransGubun>
    <SaupjaNo></SaupjaNo>
    <UserStatus>1</UserStatus>
    <CAGubun></CAGubun>
    <CustGubun></CustGubun>
    <RAGubun></RAGubun>
    <IssueBank></IssueBank>
    <IssueGubun>1</IssueGubun>
    <SSRGubun>2</SSRGubun>
    <SSRFee>0</SSRFee>
    <SSRVat>0</SSRVat>
    <IssueDate>20251126</IssueDate>
    <ExpireDate>20251214</ExpireDate>
    <SecurityIndex2>000000</SecurityIndex2>
    <SafeCardIndex1>0</SafeCardIndex1>
    <SafeCardIndex2>0</SafeCardIndex2>
    <SafeCardIndex3>0</SafeCardIndex3>
    <YOHPIN>N</YOHPIN>
    <YOADRGB1>1</YOADRGB1>
    <YOZIPCD40>03150</YOZIPCD40>
    <YOZIPCD41>111103100006</YOZIPCD41>
    <YOZIPCD42>02</YOZIPCD42>
    <YOZIPCD43>0</YOZIPCD43>
    <YOZIPCD44>0008100000</YOZIPCD44>
    <YOSJUSO4>서울　종로구　삼봉로　８１　　　　　　　　　　　　　　　　　　　　　　</YOSJUSO4>
    <YOJUSO4>１２１８호　（수송동，　두산위브파빌리온）　　　　　　　　　　　　　　　　　　　　　　　　　　　　　</YOJUSO4>
    <YOIDGB>1</YOIDGB>
    <AuthSVC4TRAN>0</AuthSVC4TRAN>
    <AuthSVC4CERT>0</AuthSVC4CERT>
    <OTPStatus></OTPStatus>
    <YODRBR>860</YODRBR>
    <SmartOTP></SmartOTP>
    <YOAGREEGB></YOAGREEGB>
    <YOAGIL>0</YOAGIL>
    <YOISYN>1</YOISYN>
    <YOPAYFROM>00000000</YOPAYFROM>
    <YOPAYTO>00000000</YOPAYTO>
    <YOCFJMGB>1</YOCFJMGB>
    <YODUMY1></YODUMY1>
  </RES_DATA_PART>
</응답부>